{"Headline":{"EffectiveDate":"2023-06-25T01:00:00+06:00","EffectiveEpochDate":1687633200,"Severity":4,"Text":"Thunderstorms in the area late Saturday night through Sunday afternoon","Category":"thunderstorm","EndDate":"2023-06-25T19:00:00+06:00","EndEpochDate":1687698000,"MobileLink":"http://www.accuweather.com/en/bd/dumki-satani/27133/daily-weather-forecast/27133?unit=c&lang=en-us","Link":"http://www.accuweather.com/en/bd/dumki-satani/27133/daily-weather-forecast/27133?unit=c&lang=en-us"},"DailyForecasts":[{"Date":"2023-06-21T07:00:00+06:00","EpochDate":1687309200,"Sun":{"Rise":"2023-06-21T05:15:00+06:00","EpochRise":1687302900,"Set":"2023-06-21T18:46:00+06:00","EpochSet":1687351560},"Moon":{"Rise":"2023-06-21T07:41:00+06:00","EpochRise":1687311660,"Set":"2023-06-21T21:30:00+06:00","EpochSet":1687361400,"Phase":"WaxingCrescent","Age":3},"Temperature":{"Minimum":{"Value":27.4,"Unit":"C","UnitType":17},"Maximum":{"Value":34.1,"Unit":"C","UnitType":17}},"RealFeelTemperature":{"Minimum":{"Value":34.3,"Unit":"C","UnitType":17,"Phrase":"Hot"},"Maximum":{"Value":49.6,"Unit":"C","UnitType":17,"Phrase":"Very Dangerous Heat"}},"RealFeelTemperatureShade":{"Minimum":{"Value":34.3,"Unit":"C","UnitType":17,"Phrase":"Hot"},"Maximum":{"Value":44.4,"Unit":"C","UnitType":17,"Phrase":"Dangerous Heat"}},"HoursOfSun":3.1,"DegreeDaySummary":{"Heating":{"Value":0.0,"Unit":"C","UnitType":17},"Cooling":{"Value":13.0,"Unit":"C","UnitType":17}},"AirAndPollen":[{"Name":"AirQuality","Value":0,"Category":"Good","CategoryValue":1,"Type":"Ozone"},{"Name":"Grass","Value":0,"Category":"Low","CategoryValue":1},{"Name":"Mold","Value":0,"Category":"Low","CategoryValue":1},{"Name":"Ragweed","Value":0,"Category":"Low","CategoryValue":1},{"Name":"Tree","Value":0,"Category":"Low","CategoryValue":1},{"Name":"UVIndex","Value":10,"Category":"Very High","CategoryValue":4}],"Day":{"Icon":15,"IconPhrase":"Thunderstorms","HasPrecipitation":true,"PrecipitationType":"Rain","PrecipitationIntensity":"Moderate","ShortPhrase":"Couple of thunderstorms","LongPhrase":"Cloudy most of the time with a couple of showers and a thunderstorm, mainly later","PrecipitationProbability":84,"ThunderstormProbability":50,"RainProbability":84,"SnowProbability":0,"IceProbability":0,"Wind":{"Speed":{"Value":5.6,"Unit":"km/h","UnitType":7},"Direction":{"Degrees":169,"Localized":"S","English":"S"}},"WindGust":{"Speed":{"Value":20.4,"Unit":"km/h","UnitType":7},"Direction":{"Degrees":179,"Localized":"S","English":"S"}},"TotalLiquid":{"Value":6.2,"Unit":"mm","UnitType":3},"Rain":{"Value":6.2,"Unit":"mm","UnitType":3},"Snow":{"Value":0.0,"Unit":"cm","UnitType":4},"Ice":{"Value":0.0,"Unit":"mm","UnitType":3},"HoursOfPrecipitation":3.5,"HoursOfRain":3.5,"HoursOfSnow":0.0,"HoursOfIce":0.0,"CloudCover":84,"Evapotranspiration":{"Value":2.8,"Unit":"mm","UnitType":3},"SolarIrradiance":{"Value":3025.1,"Unit":"W/m²","UnitType":33}},"Night":{"Icon":7,"IconPhrase":"Cloudy","HasPrecipitation":false,"ShortPhrase":"Considerable cloudiness","LongPhrase":"Considerable cloudiness","PrecipitationProbability":25,"ThunderstormProbability":6,"RainProbability":25,"SnowProbability":0,"IceProbability":0,"Wind":{"Speed":{"Value":11.1,"Unit":"km/h","UnitType":7},"Direction":{"Degrees":170,"Localized":"S","English":"S"}},"WindGust":{"Speed":{"Value":25.9,"Unit":"km/h","UnitType":7},"Direction":{"Degrees":177,"Localized":"S","English":"S"}},"TotalLiquid":{"Value":0.0,"Unit":"mm","UnitType":3},"Rain":{"Value":0.0,"Unit":"mm","UnitType":3},"Snow":{"Value":0.0,"Unit":"cm","UnitType":4},"Ice":{"Value":0.0,"Unit":"mm","UnitType":3},"HoursOfPrecipitation":0.0,"HoursOfRain":0.0,"HoursOfSnow":0.0,"HoursOfIce":0.0,"CloudCover":96,"Evapotranspiration":{"Value":0.3,"Unit":"mm","UnitType":3},"SolarIrradiance":{"Value":8.3,"Unit":"W/m²","UnitType":33}},"Sources":["AccuWeather"],"MobileLink":"http://www.accuweather.com/en/bd/dumki-satani/27133/daily-weather-forecast/27133?day=1&unit=c&lang=en-us","Link":"http://www.accuweather.com/en/bd/dumki-satani/27133/daily-weather-forecast/27133?day=1&unit=c&lang=en-us"},{"Date":"2023-06-22T07:00:00+06:00","EpochDate":1687395600,"Sun":{"Rise":"2023-06-22T05:15:00+06:00","EpochRise":1687389300,"Set":"2023-06-22T18:46:00+06:00","EpochSet":1687437960},"Moon":{"Rise":"2023-06-22T08:34:00+06:00","EpochRise":1687401240,"Set":"2023-06-22T22:08:00+06:00","EpochSet":1687450080,"Phase":"WaxingCrescent","Age":4},"Temperature":{"Minimum":{"Value":26.4,"Unit":"C","UnitType":17},"Maximum":{"Value":33.9,"Unit":"C","UnitType":17}},"RealFeelTemperature":{"Minimum":{"Value":31.1,"Unit":"C","UnitType":17,"Phrase":"Very Warm"},"Maximum":{"Value":41.8,"Unit":"C","UnitType":17,"Phrase":"Dangerous Heat"}},"RealFeelTemperatureShade":{"Minimum":{"Value":31.1,"Unit":"C","UnitType":17,"Phrase":"Very Warm"},"Maximum":{"Value":40.1,"Unit":"C","UnitType":17,"Phrase":"Very Hot"}},"HoursOfSun":2.1,"DegreeDaySummary":{"Heating":{"Value":0.0,"Unit":"C","UnitType":17},"Cooling":{"Value":12.0,"Unit":"C","UnitType":17}},"AirAndPollen":[{"Name":"AirQuality","Value":0,"Category":"Good","CategoryValue":1,"Type":"Ozone"},{"Name":"Grass","Value":0,"Category":"Low","CategoryValue":1},{"Name":"Mold","Value":0,"Category":"Low","CategoryValue":1},{"Name":"Ragweed","Value":0,"Category":"Low","CategoryValue":1},{"Name":"Tree","Value":0,"Category":"Low","CategoryValue":1},{"Name":"UVIndex","Value":4,"Category":"Moderate","CategoryValue":2}],"Day":{"Icon":15,"IconPhrase":"Thunderstorms","HasPrecipitation":true,"PrecipitationType":"Rain","PrecipitationIntensity":"Light","ShortPhrase":"Couple of thunderstorms","LongPhrase":"Rather cloudy with a couple of showers and a thunderstorm, mainly early in the day","PrecipitationProbability":78,"ThunderstormProbability":47,"RainProbability":78,"SnowProbability":0,"IceProbability":0,"Wind":{"Speed":{"Value":14.8,"Unit":"km/h","UnitType":7},"Direction":{"Degrees":169,"Localized":"S","English":"S"}},"WindGust":{"Speed":{"Value":37.0,"Unit":"km/h","UnitType":7},"Direction":{"Degrees":161,"Localized":"SSE","English":"SSE"}},"TotalLiquid":{"Value":2.9,"Unit":"mm","UnitType":3},"Rain":{"Value":2.9,"Unit":"mm","UnitType":3},"Snow":{"Value":0.0,"Unit":"cm","UnitType":4},"Ice":{"Value":0.0,"Unit":"mm","UnitType":3},"HoursOfPrecipitation":1.5,"HoursOfRain":1.5,"HoursOfSnow":0.0,"HoursOfIce":0.0,"CloudCover":94,"Evapotranspiration":{"Value":3.0,"Unit":"mm","UnitType":3},"SolarIrradiance":{"Value":2078.3,"Unit":"W/m²","UnitType":33}},"Night":{"Icon":42,"IconPhrase":"Mostly cloudy w/ t-storms","HasPrecipitation":true,"PrecipitationType":"Rain","PrecipitationIntensity":"Moderate","ShortPhrase":"A couple of t-storms late","LongPhrase":"Partly to mostly cloudy with a thunderstorm or two late","PrecipitationProbability":78,"ThunderstormProbability":47,"RainProbability":78,"SnowProbability":0,"IceProbability":0,"Wind":{"Speed":{"Value":13.0,"Unit":"km/h","UnitType":7},"Direction":{"Degrees":192,"Localized":"SSW","English":"SSW"}},"WindGust":{"Speed":{"Value":27.8,"Unit":"km/h","UnitType":7},"Direction":{"Degrees":196,"Localized":"SSW","English":"SSW"}},"TotalLiquid":{"Value":8.3,"Unit":"mm","UnitType":3},"Rain":{"Value":8.3,"Unit":"mm","UnitType":3},"Snow":{"Value":0.0,"Unit":"cm","UnitType":4},"Ice":{"Value":0.0,"Unit":"mm","UnitType":3},"HoursOfPrecipitation":2.0,"HoursOfRain":2.0,"HoursOfSnow":0.0,"HoursOfIce":0.0,"CloudCover":100,"Evapotranspiration":{"Value":0.3,"Unit":"mm","UnitType":3},"SolarIrradiance":{"Value":8.3,"Unit":"W/m²","UnitType":33}},"Sources":["AccuWeather"],"MobileLink":"http://www.accuweather.com/en/bd/dumki-satani/27133/daily-weather-forecast/27133?day=2&unit=c&lang=en-us","Link":"http://www.accuweather.com/en/bd/dumki-satani/27133/daily-weather-forecast/27133?day=2&unit=c&lang=en-us"},{"Date":"2023-06-23T07:00:00+06:00","EpochDate":1687482000,"Sun":{"Rise":"2023-06-23T05:15:00+06:00","EpochRise":1687475700,"Set":"2023-06-23T18:46:00+06:00","EpochSet":1687524360},"Moon":{"Rise":"2023-06-23T09:28:00+06:00","EpochRise":1687490880,"Set":"2023-06-23T22:42:00+06:00","EpochSet":1687538520,"Phase":"WaxingCrescent","Age":5},"Temperature":{"Minimum":{"Value":26.8,"Unit":"C","UnitType":17},"Maximum":{"Value":32.6,"Unit":"C","UnitType":17}},"RealFeelTemperature":{"Minimum":{"Value":31.9,"Unit":"C","UnitType":17,"Phrase":"Hot"},"Maximum":{"Value":39.1,"Unit":"C","UnitType":17,"Phrase":"Very Hot"}},"RealFeelTemperatureShade":{"Minimum":{"Value":31.9,"Unit":"C","UnitType":17,"Phrase":"Hot"},"Maximum":{"Value":37.5,"Unit":"C","UnitType":17,"Phrase":"Very Hot"}},"HoursOfSun":2.5,"DegreeDaySummary":{"Heating":{"Value":0.0,"Unit":"C","UnitType":17},"Cooling":{"Value":12.0,"Unit":"C","UnitType":17}},"AirAndPollen":[{"Name":"AirQuality","Value":0,"Category":"Good","CategoryValue":1,"Type":"Ozone"},{"Name":"Grass","Value":0,"Category":"Low","CategoryValue":1},{"Name":"Mold","Value":0,"Category":"Low","CategoryValue":1},{"Name":"Ragweed","Value":0,"Category":"Low","CategoryValue":1},{"Name":"Tree","Value":0,"Category":"Low","CategoryValue":1},{"Name":"UVIndex","Value":3,"Category":"Moderate","CategoryValue":2}],"Day":{"Icon":15,"IconPhrase":"Thunderstorms","HasPrecipitation":true,"PrecipitationType":"Rain","PrecipitationIntensity":"Moderate","ShortPhrase":"A shower and thunderstorm","LongPhrase":"Mostly cloudy with a couple of showers and a thunderstorm","PrecipitationProbability":88,"ThunderstormProbability":53,"RainProbability":88,"SnowProbability":0,"IceProbability":0,"Wind":{"Speed":{"Value":16.7,"Unit":"km/h","UnitType":7},"Direction":{"Degrees":148,"Localized":"SSE","English":"SSE"}},"WindGust":{"Speed":{"Value":31.5,"Unit":"km/h","UnitType":7},"Direction":{"Degrees":149,"Localized":"SSE","English":"SSE"}},"TotalLiquid":{"Value":5.3,"Unit":"mm","UnitType":3},"Rain":{"Value":5.3,"Unit":"mm","UnitType":3},"Snow":{"Value":0.0,"Unit":"cm","UnitType":4},"Ice":{"Value":0.0,"Unit":"mm","UnitType":3},"HoursOfPrecipitation":4.0,"HoursOfRain":4.0,"HoursOfSnow":0.0,"HoursOfIce":0.0,"CloudCover":94,"Evapotranspiration":{"Value":3.0,"Unit":"mm","UnitType":3},"SolarIrradiance":{"Value":2078.2,"Unit":"W/m²","UnitType":33}},"Night":{"Icon":40,"IconPhrase":"Mostly cloudy w/ showers","HasPrecipitation":true,"PrecipitationType":"Rain","PrecipitationIntensity":"Moderate","ShortPhrase":"Some rain and a t-storm late","LongPhrase":"Partly to mostly cloudy with occasional rain and a thunderstorm late","PrecipitationProbability":60,"ThunderstormProbability":36,"RainProbability":60,"SnowProbability":0,"IceProbability":0,"Wind":{"Speed":{"Value":11.1,"Unit":"km/h","UnitType":7},"Direction":{"Degrees":154,"Localized":"SSE","English":"SSE"}},"WindGust":{"Speed":{"Value":24.1,"Unit":"km/h","UnitType":7},"Direction":{"Degrees":168,"Localized":"SSE","English":"SSE"}},"TotalLiquid":{"Value":2.6,"Unit":"mm","UnitType":3},"Rain":{"Value":2.6,"Unit":"mm","UnitType":3},"Snow":{"Value":0.0,"Unit":"cm","UnitType":4},"Ice":{"Value":0.0,"Unit":"mm","UnitType":3},"HoursOfPrecipitation":2.0,"HoursOfRain":2.0,"HoursOfSnow":0.0,"HoursOfIce":0.0,"CloudCover":84,"Evapotranspiration":{"Value":0.3,"Unit":"mm","UnitType":3},"SolarIrradiance":{"Value":124.9,"Unit":"W/m²","UnitType":33}},"Sources":["AccuWeather"],"MobileLink":"http://www.accuweather.com/en/bd/dumki-satani/27133/daily-weather-forecast/27133?day=3&unit=c&lang=en-us","Link":"http://www.accuweather.com/en/bd/dumki-satani/27133/daily-weather-forecast/27133?day=3&unit=c&lang=en-us"},{"Date":"2023-06-24T07:00:00+06:00","EpochDate":1687568400,"Sun":{"Rise":"2023-06-24T05:15:00+06:00","EpochRise":1687562100,"Set":"2023-06-24T18:46:00+06:00","EpochSet":1687610760},"Moon":{"Rise":"2023-06-24T10:18:00+06:00","EpochRise":1687580280,"Set":"2023-06-24T23:14:00+06:00","EpochSet":1687626840,"Phase":"WaxingCrescent","Age":6},"Temperature":{"Minimum":{"Value":27.0,"Unit":"C","UnitType":17},"Maximum":{"Value":33.6,"Unit":"C","UnitType":17}},"RealFeelTemperature":{"Minimum":{"Value":29.7,"Unit":"C","UnitType":17,"Phrase":"Very Warm"},"Maximum":{"Value":42.7,"Unit":"C","UnitType":17,"Phrase":"Dangerous Heat"}},"RealFeelTemperatureShade":{"Minimum":{"Value":29.7,"Unit":"C","UnitType":17,"Phrase":"Very Warm"},"Maximum":{"Value":40.1,"Unit":"C","UnitType":17,"Phrase":"Very Hot"}},"HoursOfSun":2.4,"DegreeDaySummary":{"Heating":{"Value":0.0,"Unit":"C","UnitType":17},"Cooling":{"Value":12.0,"Unit":"C","UnitType":17}},"AirAndPollen":[{"Name":"AirQuality","Value":0,"Category":"Good","CategoryValue":1,"Type":"Ozone"},{"Name":"Grass","Value":0,"Category":"Low","CategoryValue":1},{"Name":"Mold","Value":0,"Category":"Low","CategoryValue":1},{"Name":"Ragweed","Value":0,"Category":"Low","CategoryValue":1},{"Name":"Tree","Value":0,"Category":"Low","CategoryValue":1},{"Name":"UVIndex","Value":6,"Category":"High","CategoryValue":3}],"Day":{"Icon":15,"IconPhrase":"Thunderstorms","HasPrecipitation":true,"PrecipitationType":"Rain","PrecipitationIntensity":"Moderate","ShortPhrase":"A shower and thunderstorm","LongPhrase":"Mostly cloudy with a couple of showers and a thunderstorm","PrecipitationProbability":88,"ThunderstormProbability":53,"RainProbability":88,"SnowProbability":0,"IceProbability":0,"Wind":{"Speed":{"Value":20.4,"Unit":"km/h","UnitType":7},"Direction":{"Degrees":153,"Localized":"SSE","English":"SSE"}},"WindGust":{"Speed":{"Value":31.5,"Unit":"km/h","UnitType":7},"Direction":{"Degrees":152,"Localized":"SSE","English":"SSE"}},"TotalLiquid":{"Value":10.7,"Unit":"mm","UnitType":3},"Rain":{"Value":10.7,"Unit":"mm","UnitType":3},"Snow":{"Value":0.0,"Unit":"cm","UnitType":4},"Ice":{"Value":0.0,"Unit":"mm","UnitType":3},"HoursOfPrecipitation":4.0,"HoursOfRain":4.0,"HoursOfSnow":0.0,"HoursOfIce":0.0,"CloudCover":92,"Evapotranspiration":{"Value":3.0,"Unit":"mm","UnitType":3},"SolarIrradiance":{"Value":2343.8,"Unit":"W/m²","UnitType":33}},"Night":{"Icon":12,"IconPhrase":"Showers","HasPrecipitation":true,"PrecipitationType":"Rain","PrecipitationIntensity":"Heavy","ShortPhrase":"Some rain and a t-storm late","LongPhrase":"Cloudy with occasional rain and a thunderstorm late","PrecipitationProbability":80,"ThunderstormProbability":48,"RainProbability":80,"SnowProbability":0,"IceProbability":0,"Wind":{"Speed":{"Value":13.0,"Unit":"km/h","UnitType":7},"Direction":{"Degrees":151,"Localized":"SSE","English":"SSE"}},"WindGust":{"Speed":{"Value":24.1,"Unit":"km/h","UnitType":7},"Direction":{"Degrees":167,"Localized":"SSE","English":"SSE"}},"TotalLiquid":{"Value":22.7,"Unit":"mm","UnitType":3},"Rain":{"Value":22.7,"Unit":"mm","UnitType":3},"Snow":{"Value":0.0,"Unit":"cm","UnitType":4},"Ice":{"Value":0.0,"Unit":"mm","UnitType":3},"HoursOfPrecipitation":2.0,"HoursOfRain":2.0,"HoursOfSnow":0.0,"HoursOfIce":0.0,"CloudCover":100,"Evapotranspiration":{"Value":0.5,"Unit":"mm","UnitType":3},"SolarIrradiance":{"Value":8.2,"Unit":"W/m²","UnitType":33}},"Sources":["AccuWeather"],"MobileLink":"http://www.accuweather.com/en/bd/dumki-satani/27133/daily-weather-forecast/27133?day=4&unit=c&lang=en-us","Link":"http://www.accuweather.com/en/bd/dumki-satani/27133/daily-weather-forecast/27133?day=4&unit=c&lang=en-us"},{"Date":"2023-06-25T07:00:00+06:00","EpochDate":1687654800,"Sun":{"Rise":"2023-06-25T05:16:00+06:00","EpochRise":1687648560,"Set":"2023-06-25T18:46:00+06:00","EpochSet":1687697160},"Moon":{"Rise":"2023-06-25T11:08:00+06:00","EpochRise":1687669680,"Set":"2023-06-25T23:45:00+06:00","EpochSet":1687715100,"Phase":"WaxingCrescent","Age":7},"Temperature":{"Minimum":{"Value":26.5,"Unit":"C","UnitType":17},"Maximum":{"Value":31.9,"Unit":"C","UnitType":17}},"RealFeelTemperature":{"Minimum":{"Value":28.1,"Unit":"C","UnitType":17,"Phrase":"Very Warm"},"Maximum":{"Value":39.1,"Unit":"C","UnitType":17,"Phrase":"Very Hot"}},"RealFeelTemperatureShade":{"Minimum":{"Value":28.1,"Unit":"C","UnitType":17,"Phrase":"Very Warm"},"Maximum":{"Value":37.6,"Unit":"C","UnitType":17,"Phrase":"Very Hot"}},"HoursOfSun":2.1,"DegreeDaySummary":{"Heating":{"Value":0.0,"Unit":"C","UnitType":17},"Cooling":{"Value":11.0,"Unit":"C","UnitType":17}},"AirAndPollen":[{"Name":"AirQuality","Value":0,"Category":"Good","CategoryValue":1,"Type":"Ozone"},{"Name":"Grass","Value":0,"Category":"Low","CategoryValue":1},{"Name":"Mold","Value":0,"Category":"Low","CategoryValue":1},{"Name":"Ragweed","Value":0,"Category":"Low","CategoryValue":1},{"Name":"Tree","Value":0,"Category":"Low","CategoryValue":1},{"Name":"UVIndex","Value":3,"Category":"Moderate","CategoryValue":2}],"Day":{"Icon":15,"IconPhrase":"Thunderstorms","HasPrecipitation":true,"PrecipitationType":"Rain","PrecipitationIntensity":"Moderate","ShortPhrase":"A couple of thunderstorms","LongPhrase":"Mostly cloudy with a thunderstorm or two","PrecipitationProbability":88,"ThunderstormProbability":53,"RainProbability":88,"SnowProbability":0,"IceProbability":0,"Wind":{"Speed":{"Value":18.5,"Unit":"km/h","UnitType":7},"Direction":{"Degrees":127,"Localized":"SE","English":"SE"}},"WindGust":{"Speed":{"Value":35.2,"Unit":"km/h","UnitType":7},"Direction":{"Degrees":133,"Localized":"SE","English":"SE"}},"TotalLiquid":{"Value":19.5,"Unit":"mm","UnitType":3},"Rain":{"Value":19.5,"Unit":"mm","UnitType":3},"Snow":{"Value":0.0,"Unit":"cm","UnitType":4},"Ice":{"Value":0.0,"Unit":"mm","UnitType":3},"HoursOfPrecipitation":4.0,"HoursOfRain":4.0,"HoursOfSnow":0.0,"HoursOfIce":0.0,"CloudCover":94,"Evapotranspiration":{"Value":2.8,"Unit":"mm","UnitType":3},"SolarIrradiance":{"Value":2078.0,"Unit":"W/m²","UnitType":33}},"Night":{"Icon":12,"IconPhrase":"Showers","HasPrecipitation":true,"PrecipitationType":"Rain","PrecipitationIntensity":"Heavy","ShortPhrase":"Some rain and a t-storm late","LongPhrase":"Cloudy, becoming breezy late with occasional rain and a thunderstorm","PrecipitationProbability":84,"ThunderstormProbability":50,"RainProbability":84,"SnowProbability":0,"IceProbability":0,"Wind":{"Speed":{"Value":18.5,"Unit":"km/h","UnitType":7},"Direction":{"Degrees":137,"Localized":"SE","English":"SE"}},"WindGust":{"Speed":{"Value":29.6,"Unit":"km/h","UnitType":7},"Direction":{"Degrees":108,"Localized":"ESE","English":"ESE"}},"TotalLiquid":{"Value":35.4,"Unit":"mm","UnitType":3},"Rain":{"Value":35.4,"Unit":"mm","UnitType":3},"Snow":{"Value":0.0,"Unit":"cm","UnitType":4},"Ice":{"Value":0.0,"Unit":"mm","UnitType":3},"HoursOfPrecipitation":2.0,"HoursOfRain":2.0,"HoursOfSnow":0.0,"HoursOfIce":0.0,"CloudCover":100,"Evapotranspiration":{"Value":0.3,"Unit":"mm","UnitType":3},"SolarIrradiance":{"Value":8.2,"Unit":"W/m²","UnitType":33}},"Sources":["AccuWeather"],"MobileLink":"http://www.accuweather.com/en/bd/dumki-satani/27133/daily-weather-forecast/27133?day=5&unit=c&lang=en-us","Link":"http://www.accuweather.com/en/bd/dumki-satani/27133/daily-weather-forecast/27133?day=5&unit=c&lang=en-us"}]}